nonebot_plugin_mc_whitelist_controller/__init__.py
nonebot_plugin_mc_whitelist_controller/data_source.py
nonebot_plugin_mc_whitelist_controller/get_uuid.py
nonebot_plugin_mc_whitelist_controller/profile.py
nonebot_plugin_mc_whitelist_controller/register.py
nonebot_plugin_mc_whitelist_controller/registration_checker.py
nonebot_plugin_mc_whitelist_controller/unregister.py
nonebot_plugin_mc_whitelist_controller-1.0.6.dist-info/licenses/LICENSE
nonebot_plugin_mc_whitelist_controller-1.0.6.dist-info/METADATA
nonebot_plugin_mc_whitelist_controller-1.0.6.dist-info/WHEEL
nonebot_plugin_mc_whitelist_controller-1.0.6.dist-info/top_level.txt
nonebot_plugin_mc_whitelist_controller-1.0.6.dist-info/RECORD
