Metadata-Version: 2.4
Name: nonebot-plugin-mc-whitelist-controller
Version: 1.0.6
Summary: nonebot-plugin-mc-whitelist-controller
License-Expression: MIT
Project-URL: homepage, https://github.com/leaf2006/nonebot-plugin-mc-whitelist-controller
Requires-Python: <4.0,>=3.9
License-File: LICENSE
Requires-Dist: nonebot2>=2.4.4
Requires-Dist: nonebot-adapter-onebot>=2.4.6
Requires-Dist: httpx>=0.22.0
Requires-Dist: nonebot-plugin-localstore>=0.7.4
Provides-Extra: dev
Requires-Dist: pyright[nodejs]; extra == "dev"
Requires-Dist: ruff; extra == "dev"
Dynamic: license-file
